metadataclient
