Metadata-Version: 1.1
Name: murano-metadataclient
Version: 0.4.dev22.gde2fe8a
Summary: murano-metadataclient
Home-page: htts://launchpad.net/murano
Author: Mirantis, Inc.
Author-email: murano-all@lists.openstack.org
License: Apache License, Version 2.0
Platform: UNKNOWN
Classifier: Development Status :: 4 - Beta
Classifier: Environment :: Console
Classifier: Intended Audience :: Developers
Classifier: Intended Audience :: Information Technology
Classifier: License :: OSI Approved :: Apache Software License
Classifier: Operating System :: OS Independent
Classifier: Programming Language :: Python
